pyace/__init__.py
pyace/asecalc.py
pyace/atomicenvironment.py
pyace/basis.cpython-36m-x86_64-linux-gnu.so
pyace/basisextension.py
pyace/calculator.cpython-36m-x86_64-linux-gnu.so
pyace/catomicenvironment.cpython-36m-x86_64-linux-gnu.so
pyace/const.py
pyace/coupling.cpython-36m-x86_64-linux-gnu.so
pyace/evaluator.cpython-36m-x86_64-linux-gnu.so
pyace/fitadapter.py
pyace/fitcallbacks.py
pyace/generalfit.py
pyace/helpers.py
pyace/libyaml-cpp.so
pyace/libyaml-cpp.so.0.6
pyace/libyaml-cpp.so.0.6.3
pyace/paralleldataexecutor.py
pyace/preparedata.py
pyace/pyacefit.py
pyace/pyneighbor.py
pyace/radial.py
pyace/read_base_conf.py
pyace/sharmonics.cpython-36m-x86_64-linux-gnu.so
pyace/ace/__init__.py
pyace/data/__init__.py
pyace/data/pyace_selected_bbasis_funcspec.pckl.gzip
pyace/utils/__init__.py
pyace_lite-0.0.1.5.data/scripts/pace_yaml2ace
pyace_lite-0.0.1.5.data/scripts/pacemaker
pyace_lite-0.0.1.5.dist-info/LICENSE
pyace_lite-0.0.1.5.dist-info/METADATA
pyace_lite-0.0.1.5.dist-info/WHEEL
pyace_lite-0.0.1.5.dist-info/top_level.txt
pyace_lite-0.0.1.5.dist-info/RECORD
