Metadata-Version: 2.1
Name: pyace-lite
Version: 0.0.1.5
Summary: Python bindings, utilities for PACE and fitting code "pacemaker"
Home-page: https://git.noc.ruhr-uni-bochum.de/atomicclusterexpansion/pyace
Author: Yury Lysogorskiy, Anton Bochkarev, Sarath Menon, Ralf Drautz
Author-email: yury.lysogorskiy@rub.de
License: UNKNOWN
Platform: UNKNOWN
Classifier: Programming Language :: Python :: 3
